Metadata-Version: 2.4
Name: daytona_api_client
Version: 0.138.0
Summary: Daytona
Home-page: 
Author: Daytona Platforms Inc.
Author-email: support@daytona.com
Keywords: OpenAPI,OpenAPI-Generator,Daytona
License-File: LICENSE
Requires-Dist: urllib3<3.0.0,>=2.1.0
Requires-Dist: python-dateutil>=2.8.2
Requires-Dist: pydantic>=2
Requires-Dist: typing-extensions>=4.7.1
Dynamic: author
Dynamic: author-email
Dynamic: description
Dynamic: description-content-type
Dynamic: keywords
Dynamic: license-file
Dynamic: requires-dist
Dynamic: summary
